project3-ripple-carry-adder/half_adder.v
module half_adder(
    input a,
    input b,
    output sum,
    output carry
);
    assign sum = a ^ b;
    assign carry = a & b;
endmodule

project3-ripple-carry-adder/full_adder.v
module full_adder(
    input a,
    input b,
    input cin,
    output sum,
    output cout
);
    wire sum1, carry1, carry2;
    
    half_adder ha1(
        .a(a),
        .b(b),
        .sum(sum1),
        .carry(carry1)
    );
    
    half_adder ha2(
        .a(sum1),
        .b(cin),
        .sum(sum),
        .carry(carry2)
    );
    
    assign cout = carry1 | carry2;
endmodule

project3-ripple-carry-adder/ripple_carry_adder.v
// 4-bit Ripple Carry Adder
// Adds two 4-bit numbers using 4 full adders
module ripple_carry_adder(
    input [3:0] a,      // 4-bit input A
    input [3:0] b,      // 4-bit input B
    input cin,          // Carry in
    output [3:0] sum,   // 4-bit sum
    output cout         // Carry out
);
    // Internal carry wires between adders
    wire c1, c2, c3;
    
    // Bit 0 (LSB) - First full adder
    full_adder fa0(
        .a(a[0]),
        .b(b[0]),
        .cin(cin),
        .sum(sum[0]),
        .cout(c1)
    );
    
    // Bit 1
    full_adder fa1(
        .a(a[1]),
        .b(b[1]),
        .cin(c1),
        .sum(sum[1]),
        .cout(c2)
    );
    
    // Bit 2
    full_adder fa2(
        .a(a[2]),
        .b(b[2]),
        .cin(c2),
        .sum(sum[2]),
        .cout(c3)
    );
    
    // Bit 3 (MSB) - Last full adder
    full_adder fa3(
        .a(a[3]),
        .b(b[3]),
        .cin(c3),
        .sum(sum[3]),
        .cout(cout)
    );
    
endmodule

project3-ripple-carry-adder/rca_tb.v
module rca_tb;
    reg [3:0] a, b;
    reg cin;
    wire [3:0] sum;
    wire cout;
    wire [4:0] expected;
    assign expected = a + b + cin;
    
    ripple_carry_adder uut(
        .a(a),
        .b(b),
        .cin(cin),
        .sum(sum),
        .cout(cout)
    );
    
    initial begin
        $display("=== 4-BIT RIPPLE CARRY ADDER TEST ===");
        $display("Time | A    B    Cin | Sum  Cout | Expected | Status");
        $display("----------------------------------------------------------");
        
        a = 4'b0000; b = 4'b0000; cin = 0; #10;
        $display("%4t | %b %b  %b  | %b   %b   | %b     | %s",
                 $time, a, b, cin, sum, cout, expected,
                 ({cout, sum} == expected) ? "PASS" : "FAIL");
        
        a = 4'b0011; b = 4'b0101; cin = 0; #10;
        $display("%4t | %b %b  %b  | %b   %b   | %b     | %s",
                 $time, a, b, cin, sum, cout, expected,
                 ({cout, sum} == expected) ? "PASS" : "FAIL");
        
        a = 4'b1111; b = 4'b0001; cin = 0; #10;
        $display("%4t | %b %b  %b  | %b   %b   | %b     | %s",
                 $time, a, b, cin, sum, cout, expected,
                 ({cout, sum} == expected) ? "PASS" : "FAIL");
        
        a = 4'b1010; b = 4'b0101; cin = 0; #10;
        $display("%4t | %b %b  %b  | %b   %b   | %b     | %s",
                 $time, a, b, cin, sum, cout, expected,
                 ({cout, sum} == expected) ? "PASS" : "FAIL");
        
        a = 4'b1111; b = 4'b1111; cin = 0; #10;
        $display("%4t | %b %b  %b  | %b   %b   | %b     | %s",
                 $time, a, b, cin, sum, cout, expected,
                 ({cout, sum} == expected) ? "PASS" : "FAIL");
        
        a = 4'b1111; b = 4'b1111; cin = 1; #10;
        $display("%4t | %b %b  %b  | %b   %b   | %b     | %s",
                 $time, a, b, cin, sum, cout, expected,
                 ({cout, sum} == expected) ? "PASS" : "FAIL");
        
        a = 4'b0111; b = 4'b0011; cin = 1; #10;
        $display("%4t | %b %b  %b  | %b   %b   | %b     | %s",
                 $time, a, b, cin, sum, cout, expected,
                 ({cout, sum} == expected) ? "PASS" : "FAIL");
        
        a = 4'b1001; b = 4'b0110; cin = 0; #10;
        $display("%4t | %b %b  %b  | %b   %b   | %b     | %s",
                 $time, a, b, cin, sum, cout, expected,
                 ({cout, sum} == expected) ? "PASS" : "FAIL");
        
        $display("\n=== ALL TESTS COMPLETE ===");
        $finish;
    end
    
    initial begin
        $dumpfile("rca.vcd");
        $dumpvars(0, rca_tb);
    end
endmodule

project3-ripple-carry-adder/rca.vcd
$date
	Fri Jan 16 21:19:18 2026
$end
$version
	Icarus Verilog
$end
$timescale
	1s
$end
$scope module rca_tb $end
$var wire 4 ! sum [3:0] $end
$var wire 5 " expected [4:0] $end
$var wire 1 # cout $end
$var reg 4 $ a [3:0] $end
$var reg 4 % b [3:0] $end
$var reg 1 & cin $end
$scope module uut $end
$var wire 4 ' a [3:0] $end
$var wire 4 ( b [3:0] $end
$var wire 1 & cin $end
$var wire 4 ) sum [3:0] $end
$var wire 1 # cout $end
$var wire 1 * c3 $end
$var wire 1 + c2 $end
$var wire 1 , c1 $end
$scope module fa0 $end
$var wire 1 - a $end
$var wire 1 . b $end
$var wire 1 & cin $end
$var wire 1 , cout $end
$var wire 1 / sum1 $end
$var wire 1 0 sum $end
$var wire 1 1 carry2 $end
$var wire 1 2 carry1 $end
$scope module ha1 $end
$var wire 1 - a $end
$var wire 1 . b $end
$var wire 1 2 carry $end
$var wire 1 / sum $end
$upscope $end
$scope module ha2 $end
$var wire 1 / a $end
$var wire 1 & b $end
$var wire 1 1 carry $end
$var wire 1 0 sum $end
$upscope $end
$upscope $end
$scope module fa1 $end
$var wire 1 3 a $end
$var wire 1 4 b $end
$var wire 1 , cin $end
$var wire 1 + cout $end
$var wire 1 5 sum1 $end
$var wire 1 6 sum $end
$var wire 1 7 carry2 $end
$var wire 1 8 carry1 $end
$scope module ha1 $end
$var wire 1 3 a $end
$var wire 1 4 b $end
$var wire 1 8 carry $end
$var wire 1 5 sum $end
$upscope $end
$scope module ha2 $end
$var wire 1 5 a $end
$var wire 1 , b $end
$var wire 1 7 carry $end
$var wire 1 6 sum $end
$upscope $end
$upscope $end
$scope module fa2 $end
$var wire 1 9 a $end
$var wire 1 : b $end
$var wire 1 + cin $end
$var wire 1 * cout $end
$var wire 1 ; sum1 $end
$var wire 1 < sum $end
$var wire 1 = carry2 $end
$var wire 1 > carry1 $end
$scope module ha1 $end
$var wire 1 9 a $end
$var wire 1 : b $end
$var wire 1 > carry $end
$var wire 1 ; sum $end
$upscope $end
$scope module ha2 $end
$var wire 1 ; a $end
$var wire 1 + b $end
$var wire 1 = carry $end
$var wire 1 < sum $end
$upscope $end
$upscope $end
$scope module fa3 $end
$var wire 1 ? a $end
$var wire 1 @ b $end
$var wire 1 * cin $end
$var wire 1 # cout $end
$var wire 1 A sum1 $end
$var wire 1 B sum $end
$var wire 1 C carry2 $end
$var wire 1 D carry1 $end
$scope module ha1 $end
$var wire 1 ? a $end
$var wire 1 @ b $end
$var wire 1 D carry $end
$var wire 1 A sum $end
$upscope $end
$scope module ha2 $end
$var wire 1 A a $end
$var wire 1 * b $end
$var wire 1 C carry $end
$var wire 1 B sum $end
$upscope $end
$upscope $end
$upscope $end
$upscope $end
$enddefinitions $end
$comment Show the parameter values. $end
$dumpall
$end
#0
$dumpvars
0D
0C
0B
0A
0@
0?
0>
0=
0<
0;
0:
09
08
07
06
05
04
03
02
01
00
0/
0.
0-
0,
0+
0*
b0 )
b0 (
b0 '
0&
b0 %
b0 $
0#
b0 "
b0 !
$end
#10
1B
1*
1=
1+
17
0<
1,
b1000 !
b1000 )
06
1;
12
15
1.
1:
1-
13
b101 %
b101 (
b1000 "
b11 $
b11 '
#20
1#
b0 !
b0 )
0B
1C
1A
0:
19
1?
b1 %
b1 (
b10000 "
b1111 $
b1111 '
#30
0#
1B
0C
0*
1<
0=
0+
16
07
b1111 !
b1111 )
10
0,
1/
02
1:
0-
09
b101 %
b101 (
b1111 "
b1010 $
b1010 '
#40
1+
1#
00
1,
b1110 !
b1110 )
1<
1*
05
18
0A
1D
0/
12
0;
1>
14
1@
1-
19
b1111 %
b1111 (
b11110 "
b1111 $
b1111 '
#50
b1111 !
b1111 )
10
b11111 "
1&
#60
1B
b1011 !
b1011 )
0<
1=
1*
0#
1;
0>
0D
0:
0@
0?
b11 %
b11 (
b1011 "
b111 $
b111 '
#70
0*
1<
0=
0#
0,
16
07
0+
1B
0C
1/
02
15
08
1A
b1111 !
b1111 )
10
0.
1:
03
09
1?
0&
b110 %
b110 (
b1111 "
b1001 $
b1001 '
